{
    "ground_dirt":
    {
        "char": "•",
        "colour_lit": "brown",
        "colour_dim": "dark_brown"
    },
    "wall_dirt":
    {
        "char": "░",
        "colour_lit": "brown",
        "colour_dim": "dark_brown"
    },
    "ground_grass":
    {
        "char": ".",
        "colour_lit": "green",
        "colour_dim": "dark_green"
    },
    "wall_tree":
    {
        "char": "♣",
        "colour_lit": "dark_green",
        "colour_dim": "darker_green"
    },
    "wall_tent":
    {
        "char": "#",
        "colour_lit": "olive",
        "colour_dim": "dark_green"
    },
    "wall_tent_window":
    {
        "char": "=",
        "colour_lit": "olive",
        "colour_dim": "dark_green"
    }
}